<?xml version='1.0' encoding='utf-8'?>
<Model Name="VideoWallLib.OSDPort">
 <ModelTypeClass>C++</ModelTypeClass>
 <BaseModel>CDPPort</BaseModel>
 <Attributes>
  <Attribute Name="Description" Type="string" Value="Simple port example"></Attribute>
  <Attribute Description="Implementation model used." Name="Model" ReadOnly="1" Required="1" SaveOnChange="0" Type="string" Value="VideoWallLib.OSDPort"></Attribute>
  <Attribute Description="" LogEventOnChange="0" Name="TextProp" RouteMethod="RouteEvent" SaveOnChange="0" Type="string"></Attribute>
  <Attribute LogEventOnChange="0" Name="TextIndex" RouteMethod="RouteEvent" SaveOnChange="0" Type="int"></Attribute>
 </Attributes>
 <Connections>
    <Connection InputOutputHint="N" Model="OperationUtilities.ValuedConnectionExtended&lt;string&gt;" Name="Text" TypeColorHint="#22957B"></Connection>
  <Connection Model="OperationUtilities.ValuedConnectionExtended&lt;string&gt;" Name="Alignment" Value="left"></Connection>
  <Connection Model="OperationUtilities.ValuedConnectionExtended&lt;int&gt;" Name="PosX"></Connection>
  <Connection Model="OperationUtilities.ValuedConnectionExtended&lt;int&gt;" Name="PosY"></Connection>
  <Connection Model="OperationUtilities.ValuedConnectionExtended&lt;string&gt;" Name="FontName"></Connection>
  <Connection Model="OperationUtilities.ValuedConnectionExtended&lt;string&gt;" Name="FontColor" Value="1.0,1.0,1.0,1.0"></Connection>
  <Connection Model="OperationUtilities.ValuedConnectionExtended&lt;double&gt;" Name="FontSize" Value="18"></Connection>
  <Connection Model="OperationUtilities.ValuedConnectionExtended&lt;string&gt;" Name="BGColor" Value="0.0,0.0,0.0,0.6"></Connection>
  <Connection Model="OperationUtilities.ValuedConnectionExtended&lt;double&gt;" Name="Timeout"></Connection>
  <Connection Input="1" LocalName=".TextProp" Model="CDPPortConnection" Name="MapTextProp"></Connection>
  <Connection Input="0" LocalName=".TextIndex" Model="CDPPortConnection" Name="MapTextIndex"></Connection></Connections>
</Model>